README.rst
flask_heroku_mongoengine.py
setup.py
flask_heroku_mongoengine.egg-info/PKG-INFO
flask_heroku_mongoengine.egg-info/SOURCES.txt
flask_heroku_mongoengine.egg-info/dependency_links.txt
flask_heroku_mongoengine.egg-info/not-zip-safe
flask_heroku_mongoengine.egg-info/requires.txt
flask_heroku_mongoengine.egg-info/top_level.txt