Metadata-Version: 1.1
Name: flask-heroku-mongoengine
Version: 0.1.5
Summary: Heroku environment variable configurations for Flask
Home-page: https://github.com/bjackson/flask-heroku
Author: Kenneth Reitz
Author-email: me@kennethreitz.com
License: BSD
Platform: any
Classifier: Environment :: Web Environment
Classifier: Intended Audience :: Developers
Classifier: License :: OSI Approved :: BSD License
Classifier: Operating System :: OS Independent
Classifier: Programming Language :: Python
Classifier: Topic :: Internet :: WWW/HTTP :: Dynamic Content
Classifier: Topic :: Software Development :: Libraries :: Python Modules
